djangofwd_news-0.1.5.dist-info/DESCRIPTION.rst
djangofwd_news-0.1.5.dist-info/METADATA
djangofwd_news-0.1.5.dist-info/metadata.json
djangofwd_news-0.1.5.dist-info/RECORD
djangofwd_news-0.1.5.dist-info/top_level.txt
djangofwd_news-0.1.5.dist-info/WHEEL
news/admin.py
news/cms_app.py
news/models.py
news/tests.py
news/translation.py
news/urls.py
news/views.py
news/__init__.py
news/migrations/0001_initial.py
news/migrations/0001_initial.pyc
news/migrations/0002_auto__del_field_news_slug_en__del_field_news_content_en__del_field_new.py
news/migrations/0002_auto__del_field_news_slug_en__del_field_news_content_en__del_field_new.pyc
news/migrations/0003_auto__add_field_news_title_en__add_field_news_title_hr__add_field_news.py
news/migrations/0003_auto__add_field_news_title_en__add_field_news_title_hr__add_field_news.pyc
news/migrations/__init__.py
news/migrations/__init__.pyc
news/templates/news/news_content.html
news/templates/news/news_detail.html
news/templates/news/news_list.html
news/templates/news/categories/news_content_category.html
news/templates/news/categories/news_detail_category.html
news/templates/news/categories/news_list_categories.html
news/templates/news/categories/news_list_category.html
news/templates/news/templatetags/highlight_news.html
news/templates/news/templatetags/latest_news.html
news/templates/news/templatetags/latest_news_category.html
news/templates/news/templatetags/templatetags_news_content.html
news/templatetags/news_tags.py
news/templatetags/news_tags.pyc
news/templatetags/__init__.py
news/templatetags/__init__.pyc
