Metadata-Version: 2.0
Name: djangofwd-news
Version: 0.1.5
Summary: A simple Django app to conduct Web-based news.
Home-page: http://www.fwd.hr/
Author: Daniele Milani
Author-email: daniele@fwd.hr
License: MIT
Keywords: News fwd development
Platform: UNKNOWN
Classifier: Environment :: Web Environment
Classifier: Framework :: Django
Classifier: Intended Audience :: Developers
Classifier: License :: OSI Approved :: MIT License
Classifier: Operating System :: OS Independent
Classifier: Programming Language :: Python
Classifier: Programming Language :: Python :: 2
Classifier: Programming Language :: Python :: 2.6
Classifier: Programming Language :: Python :: 2.7
Classifier: Topic :: Internet :: WWW/HTTP
Classifier: Topic :: Internet :: WWW/HTTP :: Dynamic Content
Requires-Dist: Django (==1.6.11)
Requires-Dist: django-appconf (==1.0.1)
Requires-Dist: django-bootstrap-form (==3.2)
Requires-Dist: django-classy-tags (==0.6.1)
Requires-Dist: django-cms (==3.0.12)
Requires-Dist: django-jsonfield (==0.9.13)
Requires-Dist: django-modeltranslation (==0.8.1)
Requires-Dist: django-mptt (==0.6.1)
Requires-Dist: django-sekizai (==0.8.1)
Requires-Dist: django-user-accounts (==1.0.1)
Requires-Dist: djangocms-admin-style (==0.2.5)
Requires-Dist: djangocms-text-ckeditor (==2.4.3)
Requires-Dist: easy-thumbnails (==2.2)
Requires-Dist: eventlog (==0.10.0)
Requires-Dist: html5lib (==0.999)
Requires-Dist: metron (==1.3.5)
Requires-Dist: MySQL-python (==1.2.5)
Requires-Dist: Pillow (==2.8.1)
Requires-Dist: pinax-theme-bootstrap (==5.7.2)
Requires-Dist: pytz (==2015.2)
Requires-Dist: six (==1.9.0)
Requires-Dist: South (==1.0.2)
Requires-Dist: yolk (==0.4.3)
